simplepyble/__init__.py
simplepyble/__init__.pyi
simplepyble/_simplepyble.cpython-314-i386-linux-gnu.so
simplepyble/py.typed
simplepyble/server.py
simplepyble.libs/libblkid-d5c5e507.so.1.1.0
simplepyble.libs/libcap-bfab4cba.so.2.48
simplepyble.libs/libdbus-1-a7c954cb.so.3.19.7
simplepyble.libs/libgcrypt-48fc8846.so.20.2.5
simplepyble.libs/libgpg-error-7128b56a.so.0.24.2
simplepyble.libs/liblz4-de24dde8.so.1.8.3
simplepyble.libs/liblzma-a80c9abe.so.5.2.4
simplepyble.libs/libmount-50c08e05.so.1.1.0
simplepyble.libs/libpcre2-8-813ed30b.so.0.7.1
simplepyble.libs/libselinux-4ff55052.so.1
simplepyble.libs/libsystemd-df75f0d4.so.0.23.0
simplepyble.libs/libuuid-068814e4.so.1.3.0
simplepyble-0.11.0.dist-info/METADATA
simplepyble-0.11.0.dist-info/WHEEL
simplepyble-0.11.0.dist-info/top_level.txt
simplepyble-0.11.0.dist-info/RECORD
simplepyble-0.11.0.dist-info/licenses/LICENSE.md
simplepyble-0.11.0.dist-info/sboms/auditwheel.cdx.json
