Metadata-Version: 2.1
Name: simplepyble
Version: 0.11.0
Summary: The ultimate fully-fledged cross-platform BLE library, designed for simplicity and ease of use.
Home-page: https://github.com/simpleble/simpleble
Author: Kevin Dewald
Author-email: kevin@dewald.me
Platform: Windows
Platform: macOS
Platform: Linux
Classifier: License :: Free for non-commercial use
Classifier: License :: Other/Proprietary License
Classifier: Programming Language :: Python :: 3
Classifier: Programming Language :: Python :: 3.8
Classifier: Programming Language :: Python :: 3.9
Classifier: Programming Language :: Python :: 3.10
Classifier: Programming Language :: Python :: 3.11
Classifier: Programming Language :: Python :: 3.12
Classifier: Programming Language :: Python :: 3.13
Classifier: Programming Language :: Python :: 3 :: Only
Requires-Python: >=3.8
License-File: LICENSE.md
Provides-Extra: server
Requires-Dist: fastapi; extra == "server"
Requires-Dist: uvicorn; extra == "server"
Requires-Dist: pydantic; extra == "server"
